mweb/__init__.py
mweb-0.0.1.dist-info/LICENSE
mweb-0.0.1.dist-info/METADATA
mweb-0.0.1.dist-info/WHEEL
mweb-0.0.1.dist-info/top_level.txt
mweb-0.0.1.dist-info/RECORD
