Metadata-Version: 2.1
Name: mweb
Version: 0.0.1
Summary: Python Manageable Web Framework (MWeb). MWeb is a DRY full-stack framework based on PWeb framework.
Home-page: https://github.com/banglafighter/mweb
Author: Bangla Fighter
Author-email: banglafighter.com@gmail.com
License: Apache 2.0
Platform: any
Classifier: Intended Audience :: Developers
Classifier: License :: OSI Approved :: Apache Software License
Classifier: Programming Language :: Python
License-File: LICENSE
